garbanzo/__init__.py
garbanzo/errors.py
garbanzo/filter.py
garbanzo/helpers.py
garbanzo/ledger.py
garbanzo/cli/__init__.py
garbanzo/cli/download_assistant.py
garbanzo/cli/filter.py
garbanzo/cli/main.py
garbanzo/cli/normalize.py
garbanzo-0.1.0.dist-info/METADATA
garbanzo-0.1.0.dist-info/WHEEL
garbanzo-0.1.0.dist-info/entry_points.txt
garbanzo-0.1.0.dist-info/licenses/LICENSE
garbanzo-0.1.0.dist-info/RECORD
