Metadata-Version: 2.4
Name: garbanzo
Version: 0.1.0
Summary: A collection of utilities related to the beancount (plaintext accounting) framework.
Project-URL: Documentation, https://github.com/jeremander/garbanzo#readme
Project-URL: Issues, https://github.com/jeremander/garbanzo/issues
Project-URL: Source, https://github.com/jeremander/garbanzo
Author-email: Jeremy Silver <jeremys@nessiness.com>, Zach Silver <zach.silver@gradientboostedinvestments.com>
License: MIT License
License-File: LICENSE
Keywords: beancount,finance
Classifier: Programming Language :: Python
Requires-Python: >=3.11
Requires-Dist: beancount>=3
Requires-Dist: fancy-dataclass>=0.7.4
Requires-Dist: rich>=13.9
